{
  "schemaVersion": "1.0.0",
  "manifestVersion": "1.0.0",
  "locale": "pt-BR",
  "generatedAt": null,
  "items": [
    {
      "id": "engrenagem-vegetal",
      "position": 1,
      "familyId": "machine-parts",
      "familyLabel": "Peças da Máquina",
      "title": "Engrenagem vegetal",
      "shortTitle": "Engrenagem vegetal",
      "description": "Engrenagem vegetal orienta escolhas e ecos narrativos sem impor um desfecho.",
      "enabled": true,
      "defaultValue": false,
      "controlType": "switch",
      "tags": [
        "engrenagem-vegetal",
        "machine-parts"
      ],
      "narrativeAxes": [
        "machine-parts"
      ],
      "affectedQuadrants": [
        1,
        2,
        3,
        4,
        5,
        6,
        7,
        8,
        9,
        10,
        11,
        12,
        13,
        14,
        15,
        16,
        17,
        18,
        19,
        20,
        21,
        22,
        23,
        24,
        25,
        26,
        27,
        28,
        29
      ],
      "conflicts": [],
      "synergies": [],
      "futureFunction": "Ponderar versões e quadrantes no futuro motor narrativo.",
      "metadata": {}
    },
    {
      "id": "bobina-eletrica",
      "position": 2,
      "familyId": "machine-parts",
      "familyLabel": "Peças da Máquina",
      "title": "Bobina elétrica",
      "shortTitle": "Bobina elétrica",
      "description": "Bobina elétrica orienta escolhas e ecos narrativos sem impor um desfecho.",
      "enabled": true,
      "defaultValue": false,
      "controlType": "switch",
      "tags": [
        "bobina-eletrica",
        "machine-parts"
      ],
      "narrativeAxes": [
        "machine-parts"
      ],
      "affectedQuadrants": [
        1,
        2,
        3,
        4,
        5,
        6,
        7,
        8,
        9,
        10,
        11,
        12,
        13,
        14,
        15,
        16,
        17,
        18,
        19,
        20,
        21,
        22,
        23,
        24,
        25,
        26,
        27,
        28,
        29
      ],
      "conflicts": [],
      "synergies": [],
      "futureFunction": "Ponderar versões e quadrantes no futuro motor narrativo.",
      "metadata": {}
    },
    {
      "id": "ampulheta-temporal",
      "position": 3,
      "familyId": "machine-parts",
      "familyLabel": "Peças da Máquina",
      "title": "Ampulheta temporal",
      "shortTitle": "Ampulheta temporal",
      "description": "Ampulheta temporal orienta escolhas e ecos narrativos sem impor um desfecho.",
      "enabled": true,
      "defaultValue": false,
      "controlType": "switch",
      "tags": [
        "ampulheta-temporal",
        "machine-parts"
      ],
      "narrativeAxes": [
        "machine-parts"
      ],
      "affectedQuadrants": [
        1,
        2,
        3,
        4,
        5,
        6,
        7,
        8,
        9,
        10,
        11,
        12,
        13,
        14,
        15,
        16,
        17,
        18,
        19,
        20,
        21,
        22,
        23,
        24,
        25,
        26,
        27,
        28,
        29
      ],
      "conflicts": [],
      "synergies": [],
      "futureFunction": "Ponderar versões e quadrantes no futuro motor narrativo.",
      "metadata": {}
    },
    {
      "id": "tubo-vapor",
      "position": 4,
      "familyId": "machine-parts",
      "familyLabel": "Peças da Máquina",
      "title": "Tubo de vapor",
      "shortTitle": "Tubo de vapor",
      "description": "Tubo de vapor orienta escolhas e ecos narrativos sem impor um desfecho.",
      "enabled": true,
      "defaultValue": false,
      "controlType": "switch",
      "tags": [
        "tubo-vapor",
        "machine-parts"
      ],
      "narrativeAxes": [
        "machine-parts"
      ],
      "affectedQuadrants": [
        1,
        2,
        3,
        4,
        5,
        6,
        7,
        8,
        9,
        10,
        11,
        12,
        13,
        14,
        15,
        16,
        17,
        18,
        19,
        20,
        21,
        22,
        23,
        24,
        25,
        26,
        27,
        28,
        29
      ],
      "conflicts": [],
      "synergies": [],
      "futureFunction": "Ponderar versões e quadrantes no futuro motor narrativo.",
      "metadata": {}
    },
    {
      "id": "ima-pilao",
      "position": 5,
      "familyId": "machine-parts",
      "familyLabel": "Peças da Máquina",
      "title": "Ímã de pilão",
      "shortTitle": "Ímã de pilão",
      "description": "Ímã de pilão orienta escolhas e ecos narrativos sem impor um desfecho.",
      "enabled": true,
      "defaultValue": false,
      "controlType": "switch",
      "tags": [
        "ima-pilao",
        "machine-parts"
      ],
      "narrativeAxes": [
        "machine-parts"
      ],
      "affectedQuadrants": [
        1,
        2,
        3,
        4,
        5,
        6,
        7,
        8,
        9,
        10,
        11,
        12,
        13,
        14,
        15,
        16,
        17,
        18,
        19,
        20,
        21,
        22,
        23,
        24,
        25,
        26,
        27,
        28,
        29
      ],
      "conflicts": [],
      "synergies": [],
      "futureFunction": "Ponderar versões e quadrantes no futuro motor narrativo.",
      "metadata": {}
    },
    {
      "id": "espiga-condutora",
      "position": 6,
      "familyId": "machine-parts",
      "familyLabel": "Peças da Máquina",
      "title": "Espiga condutora",
      "shortTitle": "Espiga condutora",
      "description": "Espiga condutora orienta escolhas e ecos narrativos sem impor um desfecho.",
      "enabled": true,
      "defaultValue": false,
      "controlType": "switch",
      "tags": [
        "espiga-condutora",
        "machine-parts"
      ],
      "narrativeAxes": [
        "machine-parts"
      ],
      "affectedQuadrants": [
        1,
        2,
        3,
        4,
        5,
        6,
        7,
        8,
        9,
        10,
        11,
        12,
        13,
        14,
        15,
        16,
        17,
        18,
        19,
        20,
        21,
        22,
        23,
        24,
        25,
        26,
        27,
        28,
        29
      ],
      "conflicts": [],
      "synergies": [],
      "futureFunction": "Ponderar versões e quadrantes no futuro motor narrativo.",
      "metadata": {}
    },
    {
      "id": "cristal-memoria",
      "position": 7,
      "familyId": "machine-parts",
      "familyLabel": "Peças da Máquina",
      "title": "Cristal de memória",
      "shortTitle": "Cristal de memória",
      "description": "Cristal de memória orienta escolhas e ecos narrativos sem impor um desfecho.",
      "enabled": true,
      "defaultValue": false,
      "controlType": "switch",
      "tags": [
        "cristal-memoria",
        "machine-parts"
      ],
      "narrativeAxes": [
        "machine-parts"
      ],
      "affectedQuadrants": [
        1,
        2,
        3,
        4,
        5,
        6,
        7,
        8,
        9,
        10,
        11,
        12,
        13,
        14,
        15,
        16,
        17,
        18,
        19,
        20,
        21,
        22,
        23,
        24,
        25,
        26,
        27,
        28,
        29
      ],
      "conflicts": [],
      "synergies": [],
      "futureFunction": "Ponderar versões e quadrantes no futuro motor narrativo.",
      "metadata": {}
    },
    {
      "id": "sensor-brasas",
      "position": 8,
      "familyId": "machine-parts",
      "familyLabel": "Peças da Máquina",
      "title": "Sensor de brasas",
      "shortTitle": "Sensor de brasas",
      "description": "Sensor de brasas orienta escolhas e ecos narrativos sem impor um desfecho.",
      "enabled": true,
      "defaultValue": false,
      "controlType": "switch",
      "tags": [
        "sensor-brasas",
        "machine-parts"
      ],
      "narrativeAxes": [
        "machine-parts"
      ],
      "affectedQuadrants": [
        1,
        2,
        3,
        4,
        5,
        6,
        7,
        8,
        9,
        10,
        11,
        12,
        13,
        14,
        15,
        16,
        17,
        18,
        19,
        20,
        21,
        22,
        23,
        24,
        25,
        26,
        27,
        28,
        29
      ],
      "conflicts": [],
      "synergies": [],
      "futureFunction": "Ponderar versões e quadrantes no futuro motor narrativo.",
      "metadata": {}
    },
    {
      "id": "prehistoria-terrestre",
      "position": 9,
      "familyId": "world-time",
      "familyLabel": "Mundo e Tempo",
      "title": "Pré-história terrestre",
      "shortTitle": "Pré-história terrestre",
      "description": "Pré-história terrestre orienta escolhas e ecos narrativos sem impor um desfecho.",
      "enabled": true,
      "defaultValue": false,
      "controlType": "switch",
      "tags": [
        "prehistoria-terrestre",
        "world-time"
      ],
      "narrativeAxes": [
        "world-time"
      ],
      "affectedQuadrants": [
        1,
        2,
        3,
        4,
        5,
        6,
        7,
        8,
        9,
        10,
        11,
        12,
        13,
        14,
        15,
        16,
        17,
        18,
        19,
        20,
        21,
        22,
        23,
        24,
        25,
        26,
        27,
        28,
        29
      ],
      "conflicts": [],
      "synergies": [],
      "futureFunction": "Ponderar versões e quadrantes no futuro motor narrativo.",
      "metadata": {}
    },
    {
      "id": "prehistoria-aerea",
      "position": 10,
      "familyId": "world-time",
      "familyLabel": "Mundo e Tempo",
      "title": "Pré-história aérea",
      "shortTitle": "Pré-história aérea",
      "description": "Pré-história aérea orienta escolhas e ecos narrativos sem impor um desfecho.",
      "enabled": true,
      "defaultValue": false,
      "controlType": "switch",
      "tags": [
        "prehistoria-aerea",
        "world-time"
      ],
      "narrativeAxes": [
        "world-time"
      ],
      "affectedQuadrants": [
        1,
        2,
        3,
        4,
        5,
        6,
        7,
        8,
        9,
        10,
        11,
        12,
        13,
        14,
        15,
        16,
        17,
        18,
        19,
        20,
        21,
        22,
        23,
        24,
        25,
        26,
        27,
        28,
        29
      ],
      "conflicts": [],
      "synergies": [],
      "futureFunction": "Ponderar versões e quadrantes no futuro motor narrativo.",
      "metadata": {}
    },
    {
      "id": "ancestral-indigena",
      "position": 11,
      "familyId": "world-time",
      "familyLabel": "Mundo e Tempo",
      "title": "Ancestral indígena",
      "shortTitle": "Ancestral indígena",
      "description": "Ancestral indígena orienta escolhas e ecos narrativos sem impor um desfecho.",
      "enabled": true,
      "defaultValue": false,
      "controlType": "switch",
      "tags": [
        "ancestral-indigena",
        "world-time"
      ],
      "narrativeAxes": [
        "world-time"
      ],
      "affectedQuadrants": [
        1,
        2,
        3,
        4,
        5,
        6,
        7,
        8,
        9,
        10,
        11,
        12,
        13,
        14,
        15,
        16,
        17,
        18,
        19,
        20,
        21,
        22,
        23,
        24,
        25,
        26,
        27,
        28,
        29
      ],
      "conflicts": [],
      "synergies": [],
      "futureFunction": "Ponderar versões e quadrantes no futuro motor narrativo.",
      "metadata": {}
    },
    {
      "id": "historico-mestico",
      "position": 12,
      "familyId": "world-time",
      "familyLabel": "Mundo e Tempo",
      "title": "Histórico mestiço",
      "shortTitle": "Histórico mestiço",
      "description": "Histórico mestiço orienta escolhas e ecos narrativos sem impor um desfecho.",
      "enabled": true,
      "defaultValue": false,
      "controlType": "switch",
      "tags": [
        "historico-mestico",
        "world-time"
      ],
      "narrativeAxes": [
        "world-time"
      ],
      "affectedQuadrants": [
        1,
        2,
        3,
        4,
        5,
        6,
        7,
        8,
        9,
        10,
        11,
        12,
        13,
        14,
        15,
        16,
        17,
        18,
        19,
        20,
        21,
        22,
        23,
        24,
        25,
        26,
        27,
        28,
        29
      ],
      "conflicts": [],
      "synergies": [],
      "futureFunction": "Ponderar versões e quadrantes no futuro motor narrativo.",
      "metadata": {}
    },
    {
      "id": "presente-expandido",
      "position": 13,
      "familyId": "world-time",
      "familyLabel": "Mundo e Tempo",
      "title": "Presente expandido",
      "shortTitle": "Presente expandido",
      "description": "Presente expandido orienta escolhas e ecos narrativos sem impor um desfecho.",
      "enabled": true,
      "defaultValue": false,
      "controlType": "switch",
      "tags": [
        "presente-expandido",
        "world-time"
      ],
      "narrativeAxes": [
        "world-time"
      ],
      "affectedQuadrants": [
        1,
        2,
        3,
        4,
        5,
        6,
        7,
        8,
        9,
        10,
        11,
        12,
        13,
        14,
        15,
        16,
        17,
        18,
        19,
        20,
        21,
        22,
        23,
        24,
        25,
        26,
        27,
        28,
        29
      ],
      "conflicts": [],
      "synergies": [],
      "futureFunction": "Ponderar versões e quadrantes no futuro motor narrativo.",
      "metadata": {}
    },
    {
      "id": "futuro-urbano",
      "position": 14,
      "familyId": "world-time",
      "familyLabel": "Mundo e Tempo",
      "title": "Futuro urbano",
      "shortTitle": "Futuro urbano",
      "description": "Futuro urbano orienta escolhas e ecos narrativos sem impor um desfecho.",
      "enabled": true,
      "defaultValue": false,
      "controlType": "switch",
      "tags": [
        "futuro-urbano",
        "world-time"
      ],
      "narrativeAxes": [
        "world-time"
      ],
      "affectedQuadrants": [
        1,
        2,
        3,
        4,
        5,
        6,
        7,
        8,
        9,
        10,
        11,
        12,
        13,
        14,
        15,
        16,
        17,
        18,
        19,
        20,
        21,
        22,
        23,
        24,
        25,
        26,
        27,
        28,
        29
      ],
      "conflicts": [],
      "synergies": [],
      "futureFunction": "Ponderar versões e quadrantes no futuro motor narrativo.",
      "metadata": {}
    },
    {
      "id": "futuro-distopico",
      "position": 15,
      "familyId": "world-time",
      "familyLabel": "Mundo e Tempo",
      "title": "Futuro distópico",
      "shortTitle": "Futuro distópico",
      "description": "Futuro distópico orienta escolhas e ecos narrativos sem impor um desfecho.",
      "enabled": true,
      "defaultValue": false,
      "controlType": "switch",
      "tags": [
        "futuro-distopico",
        "world-time"
      ],
      "narrativeAxes": [
        "world-time"
      ],
      "affectedQuadrants": [
        1,
        2,
        3,
        4,
        5,
        6,
        7,
        8,
        9,
        10,
        11,
        12,
        13,
        14,
        15,
        16,
        17,
        18,
        19,
        20,
        21,
        22,
        23,
        24,
        25,
        26,
        27,
        28,
        29
      ],
      "conflicts": [],
      "synergies": [],
      "futureFunction": "Ponderar versões e quadrantes no futuro motor narrativo.",
      "metadata": {}
    },
    {
      "id": "paradoxo-temporal",
      "position": 16,
      "familyId": "world-time",
      "familyLabel": "Mundo e Tempo",
      "title": "Paradoxo temporal",
      "shortTitle": "Paradoxo temporal",
      "description": "Paradoxo temporal orienta escolhas e ecos narrativos sem impor um desfecho.",
      "enabled": true,
      "defaultValue": false,
      "controlType": "switch",
      "tags": [
        "paradoxo-temporal",
        "world-time"
      ],
      "narrativeAxes": [
        "world-time"
      ],
      "affectedQuadrants": [
        1,
        2,
        3,
        4,
        5,
        6,
        7,
        8,
        9,
        10,
        11,
        12,
        13,
        14,
        15,
        16,
        17,
        18,
        19,
        20,
        21,
        22,
        23,
        24,
        25,
        26,
        27,
        28,
        29
      ],
      "conflicts": [],
      "synergies": [],
      "futureFunction": "Ponderar versões e quadrantes no futuro motor narrativo.",
      "metadata": {}
    },
    {
      "id": "mandioca",
      "position": 17,
      "familyId": "kitchen-culture",
      "familyLabel": "Cozinha, Alimento e Matéria Cultural",
      "title": "Mandioca",
      "shortTitle": "Mandioca",
      "description": "Mandioca orienta escolhas e ecos narrativos sem impor um desfecho.",
      "enabled": true,
      "defaultValue": false,
      "controlType": "switch",
      "tags": [
        "mandioca",
        "kitchen-culture"
      ],
      "narrativeAxes": [
        "kitchen-culture"
      ],
      "affectedQuadrants": [
        1,
        2,
        3,
        4,
        5,
        6,
        7,
        8,
        9,
        10,
        11,
        12,
        13,
        14,
        15,
        16,
        17,
        18,
        19,
        20,
        21,
        22,
        23,
        24,
        25,
        26,
        27,
        28,
        29
      ],
      "conflicts": [],
      "synergies": [],
      "futureFunction": "Ponderar versões e quadrantes no futuro motor narrativo.",
      "metadata": {}
    },
    {
      "id": "milho",
      "position": 18,
      "familyId": "kitchen-culture",
      "familyLabel": "Cozinha, Alimento e Matéria Cultural",
      "title": "Milho",
      "shortTitle": "Milho",
      "description": "Milho orienta escolhas e ecos narrativos sem impor um desfecho.",
      "enabled": true,
      "defaultValue": false,
      "controlType": "switch",
      "tags": [
        "milho",
        "kitchen-culture"
      ],
      "narrativeAxes": [
        "kitchen-culture"
      ],
      "affectedQuadrants": [
        1,
        2,
        3,
        4,
        5,
        6,
        7,
        8,
        9,
        10,
        11,
        12,
        13,
        14,
        15,
        16,
        17,
        18,
        19,
        20,
        21,
        22,
        23,
        24,
        25,
        26,
        27,
        28,
        29
      ],
      "conflicts": [],
      "synergies": [],
      "futureFunction": "Ponderar versões e quadrantes no futuro motor narrativo.",
      "metadata": {}
    },
    {
      "id": "tapioca",
      "position": 19,
      "familyId": "kitchen-culture",
      "familyLabel": "Cozinha, Alimento e Matéria Cultural",
      "title": "Tapioca",
      "shortTitle": "Tapioca",
      "description": "Tapioca orienta escolhas e ecos narrativos sem impor um desfecho.",
      "enabled": true,
      "defaultValue": false,
      "controlType": "switch",
      "tags": [
        "tapioca",
        "kitchen-culture"
      ],
      "narrativeAxes": [
        "kitchen-culture"
      ],
      "affectedQuadrants": [
        1,
        2,
        3,
        4,
        5,
        6,
        7,
        8,
        9,
        10,
        11,
        12,
        13,
        14,
        15,
        16,
        17,
        18,
        19,
        20,
        21,
        22,
        23,
        24,
        25,
        26,
        27,
        28,
        29
      ],
      "conflicts": [],
      "synergies": [],
      "futureFunction": "Ponderar versões e quadrantes no futuro motor narrativo.",
      "metadata": {}
    },
    {
      "id": "bolo",
      "position": 20,
      "familyId": "kitchen-culture",
      "familyLabel": "Cozinha, Alimento e Matéria Cultural",
      "title": "Bolo",
      "shortTitle": "Bolo",
      "description": "Bolo orienta escolhas e ecos narrativos sem impor um desfecho.",
      "enabled": true,
      "defaultValue": false,
      "controlType": "switch",
      "tags": [
        "bolo",
        "kitchen-culture"
      ],
      "narrativeAxes": [
        "kitchen-culture"
      ],
      "affectedQuadrants": [
        1,
        2,
        3,
        4,
        5,
        6,
        7,
        8,
        9,
        10,
        11,
        12,
        13,
        14,
        15,
        16,
        17,
        18,
        19,
        20,
        21,
        22,
        23,
        24,
        25,
        26,
        27,
        28,
        29
      ],
      "conflicts": [],
      "synergies": [],
      "futureFunction": "Ponderar versões e quadrantes no futuro motor narrativo.",
      "metadata": {}
    },
    {
      "id": "panela-barro",
      "position": 21,
      "familyId": "kitchen-culture",
      "familyLabel": "Cozinha, Alimento e Matéria Cultural",
      "title": "Panela de barro",
      "shortTitle": "Panela de barro",
      "description": "Panela de barro orienta escolhas e ecos narrativos sem impor um desfecho.",
      "enabled": true,
      "defaultValue": false,
      "controlType": "switch",
      "tags": [
        "panela-barro",
        "kitchen-culture"
      ],
      "narrativeAxes": [
        "kitchen-culture"
      ],
      "affectedQuadrants": [
        1,
        2,
        3,
        4,
        5,
        6,
        7,
        8,
        9,
        10,
        11,
        12,
        13,
        14,
        15,
        16,
        17,
        18,
        19,
        20,
        21,
        22,
        23,
        24,
        25,
        26,
        27,
        28,
        29
      ],
      "conflicts": [],
      "synergies": [],
      "futureFunction": "Ponderar versões e quadrantes no futuro motor narrativo.",
      "metadata": {}
    },
    {
      "id": "forno-barro",
      "position": 22,
      "familyId": "kitchen-culture",
      "familyLabel": "Cozinha, Alimento e Matéria Cultural",
      "title": "Forno de barro",
      "shortTitle": "Forno de barro",
      "description": "Forno de barro orienta escolhas e ecos narrativos sem impor um desfecho.",
      "enabled": true,
      "defaultValue": false,
      "controlType": "switch",
      "tags": [
        "forno-barro",
        "kitchen-culture"
      ],
      "narrativeAxes": [
        "kitchen-culture"
      ],
      "affectedQuadrants": [
        1,
        2,
        3,
        4,
        5,
        6,
        7,
        8,
        9,
        10,
        11,
        12,
        13,
        14,
        15,
        16,
        17,
        18,
        19,
        20,
        21,
        22,
        23,
        24,
        25,
        26,
        27,
        28,
        29
      ],
      "conflicts": [],
      "synergies": [],
      "futureFunction": "Ponderar versões e quadrantes no futuro motor narrativo.",
      "metadata": {}
    },
    {
      "id": "traco-indigena",
      "position": 23,
      "familyId": "kitchen-culture",
      "familyLabel": "Cozinha, Alimento e Matéria Cultural",
      "title": "Traço indígena",
      "shortTitle": "Traço indígena",
      "description": "Traço indígena orienta escolhas e ecos narrativos sem impor um desfecho.",
      "enabled": true,
      "defaultValue": false,
      "controlType": "switch",
      "tags": [
        "traco-indigena",
        "kitchen-culture"
      ],
      "narrativeAxes": [
        "kitchen-culture"
      ],
      "affectedQuadrants": [
        1,
        2,
        3,
        4,
        5,
        6,
        7,
        8,
        9,
        10,
        11,
        12,
        13,
        14,
        15,
        16,
        17,
        18,
        19,
        20,
        21,
        22,
        23,
        24,
        25,
        26,
        27,
        28,
        29
      ],
      "conflicts": [],
      "synergies": [],
      "futureFunction": "Ponderar versões e quadrantes no futuro motor narrativo.",
      "metadata": {}
    },
    {
      "id": "traco-afro-portugues",
      "position": 24,
      "familyId": "kitchen-culture",
      "familyLabel": "Cozinha, Alimento e Matéria Cultural",
      "title": "Traço afro-português",
      "shortTitle": "Traço afro-português",
      "description": "Traço afro-português orienta escolhas e ecos narrativos sem impor um desfecho.",
      "enabled": true,
      "defaultValue": false,
      "controlType": "switch",
      "tags": [
        "traco-afro-portugues",
        "kitchen-culture"
      ],
      "narrativeAxes": [
        "kitchen-culture"
      ],
      "affectedQuadrants": [
        1,
        2,
        3,
        4,
        5,
        6,
        7,
        8,
        9,
        10,
        11,
        12,
        13,
        14,
        15,
        16,
        17,
        18,
        19,
        20,
        21,
        22,
        23,
        24,
        25,
        26,
        27,
        28,
        29
      ],
      "conflicts": [],
      "synergies": [],
      "futureFunction": "Ponderar versões e quadrantes no futuro motor narrativo.",
      "metadata": {}
    },
    {
      "id": "humor",
      "position": 25,
      "familyId": "atmosphere-meaning",
      "familyLabel": "Atmosfera, Sentido e Fecho Poético",
      "title": "Humor",
      "shortTitle": "Humor",
      "description": "Humor orienta escolhas e ecos narrativos sem impor um desfecho.",
      "enabled": true,
      "defaultValue": false,
      "controlType": "switch",
      "tags": [
        "humor",
        "atmosphere-meaning"
      ],
      "narrativeAxes": [
        "atmosphere-meaning"
      ],
      "affectedQuadrants": [
        1,
        2,
        3,
        4,
        5,
        6,
        7,
        8,
        9,
        10,
        11,
        12,
        13,
        14,
        15,
        16,
        17,
        18,
        19,
        20,
        21,
        22,
        23,
        24,
        25,
        26,
        27,
        28,
        29
      ],
      "conflicts": [],
      "synergies": [],
      "futureFunction": "Ponderar versões e quadrantes no futuro motor narrativo.",
      "metadata": {}
    },
    {
      "id": "assombro",
      "position": 26,
      "familyId": "atmosphere-meaning",
      "familyLabel": "Atmosfera, Sentido e Fecho Poético",
      "title": "Assombro",
      "shortTitle": "Assombro",
      "description": "Assombro orienta escolhas e ecos narrativos sem impor um desfecho.",
      "enabled": true,
      "defaultValue": false,
      "controlType": "switch",
      "tags": [
        "assombro",
        "atmosphere-meaning"
      ],
      "narrativeAxes": [
        "atmosphere-meaning"
      ],
      "affectedQuadrants": [
        1,
        2,
        3,
        4,
        5,
        6,
        7,
        8,
        9,
        10,
        11,
        12,
        13,
        14,
        15,
        16,
        17,
        18,
        19,
        20,
        21,
        22,
        23,
        24,
        25,
        26,
        27,
        28,
        29
      ],
      "conflicts": [],
      "synergies": [],
      "futureFunction": "Ponderar versões e quadrantes no futuro motor narrativo.",
      "metadata": {}
    },
    {
      "id": "perigo",
      "position": 27,
      "familyId": "atmosphere-meaning",
      "familyLabel": "Atmosfera, Sentido e Fecho Poético",
      "title": "Perigo",
      "shortTitle": "Perigo",
      "description": "Perigo orienta escolhas e ecos narrativos sem impor um desfecho.",
      "enabled": true,
      "defaultValue": false,
      "controlType": "switch",
      "tags": [
        "perigo",
        "atmosphere-meaning"
      ],
      "narrativeAxes": [
        "atmosphere-meaning"
      ],
      "affectedQuadrants": [
        1,
        2,
        3,
        4,
        5,
        6,
        7,
        8,
        9,
        10,
        11,
        12,
        13,
        14,
        15,
        16,
        17,
        18,
        19,
        20,
        21,
        22,
        23,
        24,
        25,
        26,
        27,
        28,
        29
      ],
      "conflicts": [],
      "synergies": [],
      "futureFunction": "Ponderar versões e quadrantes no futuro motor narrativo.",
      "metadata": {}
    },
    {
      "id": "melancolia",
      "position": 28,
      "familyId": "atmosphere-meaning",
      "familyLabel": "Atmosfera, Sentido e Fecho Poético",
      "title": "Melancolia",
      "shortTitle": "Melancolia",
      "description": "Melancolia orienta escolhas e ecos narrativos sem impor um desfecho.",
      "enabled": true,
      "defaultValue": false,
      "controlType": "switch",
      "tags": [
        "melancolia",
        "atmosphere-meaning"
      ],
      "narrativeAxes": [
        "atmosphere-meaning"
      ],
      "affectedQuadrants": [
        1,
        2,
        3,
        4,
        5,
        6,
        7,
        8,
        9,
        10,
        11,
        12,
        13,
        14,
        15,
        16,
        17,
        18,
        19,
        20,
        21,
        22,
        23,
        24,
        25,
        26,
        27,
        28,
        29
      ],
      "conflicts": [],
      "synergies": [],
      "futureFunction": "Ponderar versões e quadrantes no futuro motor narrativo.",
      "metadata": {}
    },
    {
      "id": "vida",
      "position": 29,
      "familyId": "atmosphere-meaning",
      "familyLabel": "Atmosfera, Sentido e Fecho Poético",
      "title": "Vida",
      "shortTitle": "Vida",
      "description": "Vida orienta escolhas e ecos narrativos sem impor um desfecho.",
      "enabled": true,
      "defaultValue": false,
      "controlType": "switch",
      "tags": [
        "vida",
        "atmosphere-meaning"
      ],
      "narrativeAxes": [
        "atmosphere-meaning"
      ],
      "affectedQuadrants": [
        1,
        2,
        3,
        4,
        5,
        6,
        7,
        8,
        9,
        10,
        11,
        12,
        13,
        14,
        15,
        16,
        17,
        18,
        19,
        20,
        21,
        22,
        23,
        24,
        25,
        26,
        27,
        28,
        29
      ],
      "conflicts": [
        "morte"
      ],
      "synergies": [],
      "futureFunction": "Ponderar versões e quadrantes no futuro motor narrativo.",
      "metadata": {}
    },
    {
      "id": "morte",
      "position": 30,
      "familyId": "atmosphere-meaning",
      "familyLabel": "Atmosfera, Sentido e Fecho Poético",
      "title": "Morte",
      "shortTitle": "Morte",
      "description": "Morte orienta escolhas e ecos narrativos sem impor um desfecho.",
      "enabled": true,
      "defaultValue": false,
      "controlType": "switch",
      "tags": [
        "morte",
        "atmosphere-meaning"
      ],
      "narrativeAxes": [
        "atmosphere-meaning"
      ],
      "affectedQuadrants": [
        1,
        2,
        3,
        4,
        5,
        6,
        7,
        8,
        9,
        10,
        11,
        12,
        13,
        14,
        15,
        16,
        17,
        18,
        19,
        20,
        21,
        22,
        23,
        24,
        25,
        26,
        27,
        28,
        29
      ],
      "conflicts": [
        "vida"
      ],
      "synergies": [],
      "futureFunction": "Ponderar versões e quadrantes no futuro motor narrativo.",
      "metadata": {}
    },
    {
      "id": "imaginacao",
      "position": 31,
      "familyId": "atmosphere-meaning",
      "familyLabel": "Atmosfera, Sentido e Fecho Poético",
      "title": "Imaginação",
      "shortTitle": "Imaginação",
      "description": "Imaginação orienta escolhas e ecos narrativos sem impor um desfecho.",
      "enabled": true,
      "defaultValue": false,
      "controlType": "switch",
      "tags": [
        "imaginacao",
        "atmosphere-meaning"
      ],
      "narrativeAxes": [
        "atmosphere-meaning"
      ],
      "affectedQuadrants": [
        1,
        2,
        3,
        4,
        5,
        6,
        7,
        8,
        9,
        10,
        11,
        12,
        13,
        14,
        15,
        16,
        17,
        18,
        19,
        20,
        21,
        22,
        23,
        24,
        25,
        26,
        27,
        28,
        29
      ],
      "conflicts": [
        "realidade"
      ],
      "synergies": [],
      "futureFunction": "Ponderar versões e quadrantes no futuro motor narrativo.",
      "metadata": {}
    },
    {
      "id": "realidade",
      "position": 32,
      "familyId": "atmosphere-meaning",
      "familyLabel": "Atmosfera, Sentido e Fecho Poético",
      "title": "Realidade",
      "shortTitle": "Realidade",
      "description": "Realidade orienta escolhas e ecos narrativos sem impor um desfecho.",
      "enabled": true,
      "defaultValue": false,
      "controlType": "switch",
      "tags": [
        "realidade",
        "atmosphere-meaning"
      ],
      "narrativeAxes": [
        "atmosphere-meaning"
      ],
      "affectedQuadrants": [
        1,
        2,
        3,
        4,
        5,
        6,
        7,
        8,
        9,
        10,
        11,
        12,
        13,
        14,
        15,
        16,
        17,
        18,
        19,
        20,
        21,
        22,
        23,
        24,
        25,
        26,
        27,
        28,
        29
      ],
      "conflicts": [
        "imaginacao"
      ],
      "synergies": [],
      "futureFunction": "Ponderar versões e quadrantes no futuro motor narrativo.",
      "metadata": {}
    }
  ]
}
